scaffoldgraph/__init__.py
scaffoldgraph/network.py
scaffoldgraph/tree.py
scaffoldgraph/analysis/__init__.py
scaffoldgraph/analysis/diversity.py
scaffoldgraph/analysis/enrichment.py
scaffoldgraph/analysis/general.py
scaffoldgraph/analysis/representation.py
scaffoldgraph/core/__init__.py
scaffoldgraph/core/fragment.py
scaffoldgraph/core/graph.py
scaffoldgraph/core/scaffold.py
scaffoldgraph/io/__init__.py
scaffoldgraph/io/dataframe.py
scaffoldgraph/io/sdf.py
scaffoldgraph/io/smiles.py
scaffoldgraph/io/supplier.py
scaffoldgraph/io/tsv.py
scaffoldgraph/prioritization/__init__.py
scaffoldgraph/prioritization/generic_rules.py
scaffoldgraph/prioritization/original_rules.py
scaffoldgraph/prioritization/prioritization_rules.py
scaffoldgraph/prioritization/prioritization_ruleset.py
scaffoldgraph/prioritization/rule_io.py
scaffoldgraph/scripts/__init__.py
scaffoldgraph/scripts/generate.py
scaffoldgraph/scripts/misc.py
scaffoldgraph/scripts/operations.py
scaffoldgraph/scripts/run.py
scaffoldgraph/utils/__init__.py
scaffoldgraph/utils/aggregate.py
scaffoldgraph/utils/bipartite.py
scaffoldgraph/utils/cache.py
scaffoldgraph/utils/logging.py
scaffoldgraph/utils/misc.py
scaffoldgraph/vis/__init__.py
scaffoldgraph/vis/base.py
scaffoldgraph/vis/utils.py
scaffoldgraph/vis/notebook/__init__.py
scaffoldgraph/vis/notebook/cytoscape.py
scaffoldgraph/vis/notebook/resources/cytoscape.json
ScaffoldGraph-1.1.2.dist-info/LICENSE
ScaffoldGraph-1.1.2.dist-info/METADATA
ScaffoldGraph-1.1.2.dist-info/WHEEL
ScaffoldGraph-1.1.2.dist-info/entry_points.txt
ScaffoldGraph-1.1.2.dist-info/top_level.txt
ScaffoldGraph-1.1.2.dist-info/RECORD
