Metadata-Version: 2.1
Name: ScaffoldGraph
Version: 1.1.2
Summary: ScaffoldGraph is an open-source cheminformatics library, built using RDKit and NetworkX for generating scaffold networks and scaffold trees.
Home-page: https://github.com/UCLCheminformatics/scaffoldgraph
Author: Oliver Scott
Author-email: oliver.scott.17@ucl.ac.uk
License: MIT
Download-URL: https://github.com/UCLCheminformatics/scaffoldgraph/archive/1.1.2.tar.gz
Keywords: rdkit,networkx,cheminformatics,scaffolds,scaffold tree,scaffold network
Platform: UNKNOWN
Classifier: License :: OSI Approved :: MIT License
Classifier: Programming Language :: Python :: 3
Classifier: Operating System :: OS Independent
Classifier: Topic :: Scientific/Engineering
Classifier: Topic :: Scientific/Engineering :: Bio-Informatics
Classifier: Topic :: Scientific/Engineering :: Chemistry
Requires-Python: >=3.6
Requires-Dist: networkx
Requires-Dist: tqdm
Requires-Dist: loguru
Requires-Dist: scipy (>=1.3.1)
Requires-Dist: matplotlib (>=2.2.2)
Requires-Dist: pytest
Provides-Extra: rdkit
Requires-Dist: rdkit-pypi ; extra == 'rdkit'
Provides-Extra: vis
Requires-Dist: ipycytoscape (>=1.2.0) ; extra == 'vis'
